{"annotations": [{"completed_by": {"username": "yonomitt", "first_name": "Yono", "last_name": "Mittlefehldt", "avatar": "https://dagshub.com/avatars/9550"}, "result": [{"id": "slWhajplJa", "type": "rectanglelabels", "value": {"x": 5.709903703703695, "y": 17.209299999999928, "width": 85.80248148148148, "height": 70.6977100775193, "rotation": 0, "rectanglelabels": ["squirrel"]}, "origin": "manual", "to_name": "image", "from_name": "label", "image_rotation": 0, "original_width": 648, "original_height": 645}], "was_cancelled": false, "ground_truth": false, "created_at": "2022-08-10T10:26:03.784301Z", "updated_at": "2022-08-10T10:26:03.784301Z", "lead_time": 42.0, "prediction": {}, "parent_prediction": null, "parent_annotation": null}], "drafts": [], "predictions": [], "data": {"image": "repo://6f8fd87c07902fe9d05adb876bcc493984d00eb5/data/images/train/squirrels_000228.jpg"}, "meta": {}}